pylark/__init__.py
pylark/_internal_helper.py
pylark/_internal_log.py
pylark/api_service_acs.py
pylark/api_service_acs_access_record_list.py
pylark/api_service_acs_access_record_photo_get.py
pylark/api_service_acs_device_list.py
pylark/api_service_acs_user_face_get.py
pylark/api_service_acs_user_face_update.py
pylark/api_service_acs_user_get.py
pylark/api_service_acs_user_list.py
pylark/api_service_acs_user_update.py
pylark/api_service_admin.py
pylark/api_service_admin_admin_dept_stats_get.py
pylark/api_service_admin_admin_user_stats_get.py
pylark/api_service_ai.py
pylark/api_service_ai_detect_face_attributes.py
pylark/api_service_ai_detect_text_language.py
pylark/api_service_ai_recognize_basic_image.py
pylark/api_service_ai_recognize_speech_file.py
pylark/api_service_ai_recognize_speech_stream.py
pylark/api_service_ai_translate_text.py
pylark/api_service_application.py
pylark/api_service_application_app_admin_user_list.py
pylark/api_service_application_app_list.py
pylark/api_service_application_app_visibility_get.py
pylark/api_service_application_app_visibility_update.py
pylark/api_service_application_is_user_admin.py
pylark/api_service_application_message_detail.py
pylark/api_service_application_message_overview.py
pylark/api_service_application_message_trend.py
pylark/api_service_application_order_get.py
pylark/api_service_application_order_list.py
pylark/api_service_application_paid_scope_check_user.py
pylark/api_service_application_usage_detail.py
pylark/api_service_application_usage_overview.py
pylark/api_service_application_usage_trend.py
pylark/api_service_application_user_admin_scope_get.py
pylark/api_service_application_user_visible_app_get.py
pylark/api_service_approval.py
pylark/api_service_approval_approval_get.py
pylark/api_service_approval_carbon_copy_create.py
pylark/api_service_approval_carbon_copy_search.py
pylark/api_service_approval_file_upload.py
pylark/api_service_approval_get_user_task_list.py
pylark/api_service_approval_instance_add_sign.py
pylark-0.0.12.dist-info/LICENSE
pylark-0.0.12.dist-info/WHEEL
pylark-0.0.12.dist-info/METADATA
pylark-0.0.12.dist-info/RECORD
