Metadata-Version: 2.1
Name: pylark
Version: 0.0.12
Summary: Feishu/Lark Open API Python Sdk, Support ALL Open API and Event Callback.
License: Apache-2.0
Author: chyroc
Author-email: chyroc@qq.com
Requires-Python: >=3.6,<4.0
Classifier: License :: OSI Approved :: Apache Software License
Classifier: Programming Language :: Python :: 3
Classifier: Programming Language :: Python :: 3.6
Classifier: Programming Language :: Python :: 3.7
Classifier: Programming Language :: Python :: 3.8
Classifier: Programming Language :: Python :: 3.9
Requires-Dist: attrs (>=21.2.0,<22.0.0)
Requires-Dist: requests (>=2.26.0,<3.0.0)
